[
  {
    "date":1767225600000,
    "menu":"Americano",
    "price":4500,
    "qty":2.0,
    "sales":9000.0,
    "weekday_en":"Thursday",
    "weekday":"목"
  },
  {
    "date":null,
    "menu":"Latte",
    "price":5000,
    "qty":1.0,
    "sales":5000.0,
    "weekday_en":null,
    "weekday":null
  },
  {
    "date":1767398400000,
    "menu":"Mocha",
    "price":null,
    "qty":3.0,
    "sales":null,
    "weekday_en":"Saturday",
    "weekday":"토"
  },
  {
    "date":null,
    "menu":"Latte",
    "price":5000,
    "qty":null,
    "sales":null,
    "weekday_en":null,
    "weekday":null
  }
]